{
    "version": "9.3.0",
    "architecture": {
        "32bit": {
            "url": "https://github.com/schollz/croc/releases/download/v9.3.0/croc_9.3.0_Windows-32bit.zip",
            "bin": [
                "croc.exe"
            ],
            "hash": "cdd6a3d743f9bdf2044056a099180608995a57c8b7b5b85b81299166fc09d2ca"
        },
        "64bit": {
            "url": "https://github.com/schollz/croc/releases/download/v9.3.0/croc_9.3.0_Windows-64bit.zip",
            "bin": [
                "croc.exe"
            ],
            "hash": "dc78f8f90c92912764db058bbdd28847d7530919610706c0c8d583df210b808c"
        }
    },
    "homepage": "https://schollz.com/software/croc/",
    "license": "MIT",
    "description": "croc is a tool that allows any two computers to simply and securely transfer files and folders."
}